Workbook

Sheet Workbook Overview
B2: Workbook Overview
B3: EXL Cloud Training Workbook — Management Reporting with Dynamic Arrays
B5: # | C5: Sheet Name | D5: Section | E5: Description | F5: Type | G5: Status
B7: Navigation & Reference (2 sheets)
B8: 1 | C8: {=MID(CELL("filename",'Workbook Overview'!A1),FIND("]",CELL("filename",'Workbook Overview'!A1))+1,255)} -> Workbook Overview | D8: Navigation | E8: Table of contents with section grouping and sheet descriptions | F8: Navigation | G8: Active
B9: =B8+1 -> 2 | C9: {=MID(CELL("filename",'Read Me'!A1),FIND("]",CELL("filename",'Read Me'!A1))+1,255)} -> Read Me | D9: Navigation | E9: Purpose, data structure, import methods, session steps, usage instructions | F9: Documentation | G9: Active
B11: Source Data & Engine (4 sheets)
B12: =B9+1 -> 3 | C12: {=MID(CELL("filename",'Fact_Financials- OG'!A1),FIND("]",CELL("filename",'Fact_Financials- OG'!A1))+1,255)} -> Fact_Financials- OG | D12: Source | E12: Original source data — unchanged baseline from data system | F12: Data Source | G12: Baseline
B13: =B12+1 -> 4 | C13: {=MID(CELL("filename",'Fact_Financials- New'!A1),FIND("]",CELL("filename",'Fact_Financials- New'!A1))+1,255)} -> Fact_Financials- New | D13: Source | E13: Working copy with tbl_Financials — Jul 2026 actuals rolled in; Aug–Dec 2026 zeroed for forecast | F13: Data Source | G13: Active
B14: =B13+1 -> 5 | C14: {=MID(CELL("filename",'Fact_Financials- Rolled Act'!A1),FIND("]",CELL("filename",'Fact_Financials- Rolled Act'!A1))+1,255)} -> Fact_Financials- Rolled Act | D14: Source | E14: Roll-forward copy — Jul 2026 actuals retained, Aug–Dec zeroed | F14: Data Source | G14: Active
B15: =B14+1 -> 6 | C15: {=MID(CELL("filename",'Dynamic Extracts'!A1),FIND("]",CELL("filename",'Dynamic Extracts'!A1))+1,255)} -> Dynamic Extracts | D15: Engine | E15: UNIQUE dimension lists, named LAMBDAs (PLSTRUCTURE/PLDATA/PLDATABY), tAccountMap lookup | F15: Engine | G15: Active
C17: Summary by Section | D17: Sheets
C18: Navigation & Reference | D18: 2
C19: Source Data & Engine | D19: 4
C20: Total Sheets | D20: =SUM(D18:D19) -> 6

Sheet Read Me
B2: Finance Data — Management Reporting Dataset
B3: Fictional sample data for the 'Practical Claude AI for Finance Professionals' training series. | E3: ScenarioKey | F3: Scenario | G3: ScenarioOrder
E4: 1 | F4: Actual | G4: 1
B5: ABOUT THIS WORKBOOK | E5: 2 | F5: Budget | G5: 2
B6: A ready-to-import star schema: one fact table and one dimension table. All figures are synthetic | E6: 3 | F6: Forecast | G6: 3
B7: and generated for teaching purposes only — they do not represent any real company or person.
B9: DATA STRUCTURE
B10: Fact_Financials (OG) — 7,812 rows. Original dataset — do not modify.
B11: Fact_Financials (New) — 7,812 rows. Working copy for the session.
B12: Dim_Scenario — Scenario lookup table (see right →)
B14: Columns:
B15: DateKey | EntityKey | AccountKey | DeptKey | ScenarioKey | Amount
B17: Coverage:
B18: • 36 months: Jan 2024 – Dec 2026 (3 full years)
B19: • 3 entities: Americas, EMEA, APAC
B20: • 8 accounts: Product Revenue, Services Revenue, COGS, Salaries & Wages, Marketing, Software & Tools, T&E, Other OpEx
B21: • 5 departments: Sales, Marketing, Operations, Finance, Research & Development
... B84: Important context about this workbook: The sheet 'Fact_Financials- New' has 7,812 rows of financial fact data in B3:G7815 (headers in B3:G3). Columns: DateKey (YYYYMMDD integer e.g. 20240131), EntityKey (Americas / EMEA / APAC), AccountKey (Product Revenue, Services Revenue, COGS, Salaries & Wages, Marketing, Software & Tools, T&E, Other OpEx), DeptKey (Sales, Marketing, Operations, Finance, R&D), ScenarioKey (1=Actual, 2=Budget, 3=Forecast), Amount (positive=revenue, negative=expense). Column A is blank margin. Net Profit = SUM(Amount) with no sign flip. Coverage: 36 months (Jan 2024 – Dec 2026), 3 entities, 8 accounts, 5 departments, 3 scenarios. Task — Build Dynamic Array extractions and LAMBDA functions: Create a new sheet called Dynamic Extracts and build the following using only dynamic array formulas (FILTER, SORT, UNIQUE, SORTBY) referencing the raw data on Fact_Financials- New. Do NOT convert the source to a Table first. Use range references B3:G7815. Build these specific extractions: 1. Unique dimension lists — Use UNIQUE() to extract each dimension into its own labelled column: - All unique EntityKey values (should return 3) - All unique AccountKey values (should return 8) - All unique DeptKey values (should return 5) - All unique DateKey values sorted ascending (should return 36) 2. Filtered subsets — Build FILTER() formulas for: - All Actuals only (ScenarioKey=1) — this should spill approximately 2,604 rows - All Actuals for Americas only (ScenarioKey=1 AND EntityKey="Americas") - Revenue accounts only (AccountKey contains "Revenue") across all scenarios - A specific month extract: e.g. Jan 2024 Actuals (DateKey=20240131, ScenarioKey=1) 3. Named LAMBDA functions — Register these as named functions in Name Manager (Formulas → Name Manager) so they are reusable: - GETSCENARIO(scenario_key) — returns all rows for a given ScenarioKey - GETENTITY(entity_name) — returns all rows for a given EntityKey - GETPERIOD(date_key, scenario_key) — returns all rows for a specific period and scenario - PLSUMMARY(entity, scenario) — returns a summarised P&L (one row per AccountKey with summed Amount) for a given entity and scenario across all periods 4. Best practice notes — Add a header block at the top of the sheet explaining: - Dynamic arrays spill automatically — do not put anything below or to the right of a spill range - These formulas recalculate live — any change to the source data flows through instantly - LAMBDAs are reusable across the entire workbook once registered - Trade-off vs Table: no auto-expand on new rows, but more flexible for ad-hoc slicing - Performance consideration: FILTER() over 7,812 rows is fine, but would degrade at 100k+ 5. Validation — Add a small check block confirming: - ROWS(Actuals filter) + ROWS(Budget filter) + ROWS(Forecast filter) = 7,812 - SUM of filtered Actuals Amount = SUM of SUMIFS against source for ScenarioKey=1

Sheet Fact_Financials- OG
B2: Fact_Financials — Original (Do Not Modify)
B3: DateKey | C3: EntityKey | D3: AccountKey | E3: DeptKey | F3: ScenarioKey | G3: Amount
B4: 20240131 | C4: Americas | D4: Product Revenue | E4: Sales | F4: 1 | G4: 656646
B5: 20240131 | C5: Americas | D5: Product Revenue | E5: Sales | F5: 2 | G5: 671674
B6: 20240131 | C6: Americas | D6: Product Revenue | E6: Marketing | F6: 1 | G6: 101505
B7: 20240131 | C7: Americas | D7: Product Revenue | E7: Marketing | F7: 2 | G7: 111946
B8: 20240131 | C8: Americas | D8: Product Revenue | E8: Operations | F8: 1 | G8: 314202
B9: 20240131 | C9: Americas | D9: Product Revenue | E9: Operations | F9: 2 | G9: 335837
B10: 20240131 | C10: EMEA | D10: Product Revenue | E10: Sales | F10: 1 | G10: 444010
B11: 20240131 | C11: EMEA | D11: Product Revenue | E11: Sales | F11: 2 | G11: 477635
B12: 20240131 | C12: EMEA | D12: Product Revenue | E12: Marketing | F12: 1 | G12: 78716
B13: 20240131 | C13: EMEA | D13: Product Revenue | E13: Marketing | F13: 2 | G13: 79606
B14: 20240131 | C14: EMEA | D14: Product Revenue | E14: Operations | F14: 1 | G14: 234501
B15: 20240131 | C15: EMEA | D15: Product Revenue | E15: Operations | F15: 2 | G15: 238817
... B7815: 20261231 | C7815: APAC | D7815: Other Operating Expenses | E7815: Operations | F7815: 3 | G7815: -15066

Sheet Fact_Financials- New
B2: Fact_Financials — Working Copy
B3: DateKey | C3: EntityKey | D3: AccountKey | E3: DeptKey | F3: ScenarioKey | G3: Amount
B4: 20240131 | C4: Americas | D4: Product Revenue | E4: Sales | F4: 1 | G4: 656646
B5: 20240131 | C5: Americas | D5: Product Revenue | E5: Sales | F5: 2 | G5: 671674
B6: 20240131 | C6: Americas | D6: Product Revenue | E6: Marketing | F6: 1 | G6: 101505
B7: 20240131 | C7: Americas | D7: Product Revenue | E7: Marketing | F7: 2 | G7: 111946
B8: 20240131 | C8: Americas | D8: Product Revenue | E8: Operations | F8: 1 | G8: 314202
B9: 20240131 | C9: Americas | D9: Product Revenue | E9: Operations | F9: 2 | G9: 335837
B10: 20240131 | C10: EMEA | D10: Product Revenue | E10: Sales | F10: 1 | G10: 444010
B11: 20240131 | C11: EMEA | D11: Product Revenue | E11: Sales | F11: 2 | G11: 477635
B12: 20240131 | C12: EMEA | D12: Product Revenue | E12: Marketing | F12: 1 | G12: 78716
B13: 20240131 | C13: EMEA | D13: Product Revenue | E13: Marketing | F13: 2 | G13: 79606
B14: 20240131 | C14: EMEA | D14: Product Revenue | E14: Operations | F14: 1 | G14: 234501
B15: 20240131 | C15: EMEA | D15: Product Revenue | E15: Operations | F15: 2 | G15: 238817
... B7815: 20261231 | C7815: APAC | D7815: Other Operating Expenses | E7815: Operations | F7815: 3 | G7815: -15066

Sheet Fact_Financials- Rolled Act
B2: Fact_Financials — Rolled Actuals
B3: DateKey | C3: EntityKey | D3: AccountKey | E3: DeptKey | F3: ScenarioKey | G3: Amount
B4: 20240131 | C4: Americas | D4: Product Revenue | E4: Sales | F4: 1 | G4: 656646
B5: 20240131 | C5: Americas | D5: Product Revenue | E5: Sales | F5: 2 | G5: 671674
B6: 20240131 | C6: Americas | D6: Product Revenue | E6: Marketing | F6: 1 | G6: 101505
B7: 20240131 | C7: Americas | D7: Product Revenue | E7: Marketing | F7: 2 | G7: 111946
B8: 20240131 | C8: Americas | D8: Product Revenue | E8: Operations | F8: 1 | G8: 314202
B9: 20240131 | C9: Americas | D9: Product Revenue | E9: Operations | F9: 2 | G9: 335837
B10: 20240131 | C10: EMEA | D10: Product Revenue | E10: Sales | F10: 1 | G10: 444010
B11: 20240131 | C11: EMEA | D11: Product Revenue | E11: Sales | F11: 2 | G11: 477635
B12: 20240131 | C12: EMEA | D12: Product Revenue | E12: Marketing | F12: 1 | G12: 78716
B13: 20240131 | C13: EMEA | D13: Product Revenue | E13: Marketing | F13: 2 | G13: 79606
B14: 20240131 | C14: EMEA | D14: Product Revenue | E14: Operations | F14: 1 | G14: 234501
B15: 20240131 | C15: EMEA | D15: Product Revenue | E15: Operations | F15: 2 | G15: 238817
... B7815: 20261231 | C7815: APAC | D7815: Other Operating Expenses | E7815: Operations | F7815: 3 | G7815: -15066

Sheet Dynamic Extracts
B2: Dynamic Extracts
B3: Dynamic array formulas (FILTER, SORT, UNIQUE) and named LAMBDA functions referencing Fact_Financials- New.
B5: BEST PRACTICES
B6: • Dynamic arrays spill automatically — do not put anything below or to the right of a spill range.
B7: • These formulas recalculate live — any change to the source data on Fact_Financials- New flows through instantly.
B8: • LAMBDAs are reusable across the entire workbook once registered in Name Manager (Formulas → Name Manager).
B9: • Trade-off vs Table: no auto-expand on new rows, but more flexible for ad-hoc slicing without creating pivot tables.
B10: • Performance: FILTER() over 7,812 rows is fast. Above 100k+ rows, consider Power Query or pivot tables instead.
B12: 1. UNIQUE DIMENSION LISTS | J12: 3. NAMED LAMBDA FUNCTIONS (3 Active)
B13: EntityKey | D13: AccountKey | F13: DeptKey | H13: DateKey (sorted) | J13: Function | K13: Syntax | L13: Description
B14: {=_xlfn._xlws.SORT(_xlfn.UNIQUE('Fact_Financials- New'!C4:C7815))} -> Americas | D14: {=_xlfn._xlws.SORT(_xlfn.UNIQUE('Fact_Financials- New'!D4:D7815))} -> Cost of Goods Sold | F14: {=_xlfn._xlws.SORT(_xlfn.UNIQUE('Fact_Financials- New'!E4:E7815))} -> Finance | H14: {=_xlfn._xlws.SORT(_xlfn.UNIQUE('Fact_Financials- New'!B4:B7815))} -> 20240131 | J14: PLSTRUCTURE | K14: =PLSTRUCTURE() | L14: Builds P&L row labels dynamically from tAccountMap: Revenue accounts → Total Revenue → COGS → Gross Profit → OpEx → Total OpEx → Net Profit. Used as the label spine for every P&L block.
B15: APAC | D15: Marketing & Advertising | F15: Marketing | H15: 20240229 | J15: PLDATA | K15: =PLDATA(dates, scenario) | L15: Group-level P&L data block. Returns a MAKEARRAY (n×m) of amounts for all accounts × all dates. Subtotals (Total Revenue, Gross Profit, Total OpEx, Net Profit) computed from source via SUMPRODUCT.
B16: EMEA | D16: Other Operating Expenses | F16: Operations | H16: 20240331 | J16: PLDATABY | K16: =PLDATABY(dates, scenario, entity) | L16: Entity-level P&L data block. Same as PLDATA but adds an EntityKey filter. Entity name should come from a cell reference, not hardcoded.
D17: Product Revenue | F17: Research & Development | H17: 20240430
D18: Salaries & Wages | F18: Sales | H18: 20240531
D19: Services Revenue | H19: 20240630
D20: Software & Tools | H20: 20240731
D21: Travel & Entertainment | H21: 20240831
H22: 20240930
H23: 20241031
H24: 20241130 | J24: 5. P&L ACCOUNT MAP
H25: 20241231 | J25: Controls the dynamic P&L structure. Add a row here → report auto-expands.
H26: 20250131
H27: 20250228 | J27: AccountKey | K27: Category | L27: SortOrder
H28: 20250331 | J28: Product Revenue | K28: Revenue | L28: 1
H29: 20250430 | J29: Services Revenue | K29: Revenue | L29: 2
H30: 20250531 | J30: Cost of Goods Sold | K30: COGS | L30: 3
H31: 20250630 | J31: Salaries & Wages | K31: OpEx | L31: 4
H32: 20250731 | J32: Marketing & Advertising | K32: OpEx | L32: 5
H33: 20250831 | J33: Software & Tools | K33: OpEx | L33: 6
H34: 20250930 | J34: Travel & Entertainment | K34: OpEx | L34: 7
H35: 20251031 | J35: Other Operating Expenses | K35: OpEx | L35: 8
H36: 20251130
H37: 20251231
H38: 20260131
H39: 20260228
H40: 20260331
H41: 20260430
H42: 20260531
H43: 20260630
H44: 20260731
H45: 20260831
H46: 20260930
H47: 20261031
... H49: 20261231
B52: 2. FILTERED SUBSETS
B53: Filter A — Jan 2024 Actuals (DateKey=20240131, ScenarioKey=1) | H53: ="Rows: "&ROWS(_xlfn.ANCHORARRAY(B55)) -> Rows: 93
B54: DateKey | C54: EntityKey | D54: AccountKey | E54: DeptKey | F54: ScenarioKey | G54: Amount
B55: {=_xlfn._xlws.FILTER('Fact_Financials- New'!B4:G7815,('Fact_Financials- New'!B4:B7815=20240131)*('Fact_Financials- New'!F4:F7815=1))} -> 20240131 | C55: Americas | D55: Product Revenue | E55: Sales | F55: 1 | G55: 656646
B56: 20240131 | C56: Americas | D56: Product Revenue | E56: Marketing | F56: 1 | G56: 101505
B57: 20240131 | C57: Americas | D57: Product Revenue | E57: Operations | F57: 1 | G57: 314202
B58: 20240131 | C58: EMEA | D58: Product Revenue | E58: Sales | F58: 1 | G58: 444010
B59: 20240131 | C59: EMEA | D59: Product Revenue | E59: Marketing | F59: 1 | G59: 78716
B60: 20240131 | C60: EMEA | D60: Product Revenue | E60: Operations | F60: 1 | G60: 234501
B61: 20240131 | C61: APAC | D61: Product Revenue | E61: Sales | F61: 1 | G61: 345631
B62: 20240131 | C62: APAC | D62: Product Revenue | E62: Marketing | F62: 1 | G62: 52289
B63: 20240131 | C63: APAC | D63: Product Revenue | E63: Operations | F63: 1 | G63: 163502
B64: 20240131 | C64: Americas | D64: Services Revenue | E64: Sales | F64: 1 | G64: 253916
B65: 20240131 | C65: Americas | D65: Services Revenue | E65: Marketing | F65: 1 | G65: 78004
B66: 20240131 | C66: Americas | D66: Services Revenue | E66: Operations | F66: 1 | G66: 188491
B67: 20240131 | C67: EMEA | D67: Services Revenue | E67: Sales | F67: 1 | G67: 180488
... B147: 20240131 | C147: APAC | D147: Other Operating Expenses | E147: Operations | F147: 1 | G147: -10998
B150: Filter B — Americas Actuals (ScenarioKey=1, EntityKey="Americas") | H150: ="Rows: "&ROWS(_xlfn.ANCHORARRAY(B152)) -> Rows: 1116
B151: DateKey | C151: EntityKey | D151: AccountKey | E151: DeptKey | F151: ScenarioKey | G151: Amount
B152: {=_xlfn._xlws.FILTER('Fact_Financials- New'!B4:G7815,('Fact_Financials- New'!F4:F7815=1)*('Fact_Financials- New'!C4:C7815="Americas"))} -> 20240131 | C152: Americas | D152: Product Revenue | E152: Sales | F152: 1 | G152: 656646
B153: 20240131 | C153: Americas | D153: Product Revenue | E153: Marketing | F153: 1 | G153: 101505
B154: 20240131 | C154: Americas | D154: Product Revenue | E154: Operations | F154: 1 | G154: 314202
B155: 20240131 | C155: Americas | D155: Services Revenue | E155: Sales | F155: 1 | G155: 253916
B156: 20240131 | C156: Americas | D156: Services Revenue | E156: Marketing | F156: 1 | G156: 78004
B157: 20240131 | C157: Americas | D157: Services Revenue | E157: Operations | F157: 1 | G157: 188491
B158: 20240131 | C158: Americas | D158: Cost of Goods Sold | E158: Sales | F158: 1 | G158: -104216
B159: 20240131 | C159: Americas | D159: Cost of Goods Sold | E159: Operations | F159: 1 | G159: -850808
B160: 20240131 | C160: Americas | D160: Salaries & Wages | E160: Sales | F160: 1 | G160: -274133
B161: 20240131 | C161: Americas | D161: Salaries & Wages | E161: Marketing | F161: 1 | G161: -127390
B162: 20240131 | C162: Americas | D162: Salaries & Wages | E162: Research & Development | F162: 1 | G162: -205979
B163: 20240131 | C163: Americas | D163: Salaries & Wages | E163: Finance | F163: 1 | G163: -82433
B164: 20240131 | C164: Americas | D164: Salaries & Wages | E164: Operations | F164: 1 | G164: -180474
... B1267: 20261231 | C1267: Americas | D1267: Other Operating Expenses | E1267: Operations | F1267: 1 | G1267: 0
B1270: Filter C — Revenue accounts only (AccountKey contains "Revenue", all scenarios) | H1270: ="Rows: "&ROWS(_xlfn.ANCHORARRAY(B1272)) -> Rows: 1512
B1271: DateKey | C1271: EntityKey | D1271: AccountKey | E1271: DeptKey | F1271: ScenarioKey | G1271: Amount
B1272: {=_xlfn._xlws.FILTER('Fact_Financials- New'!B4:G7815,ISNUMBER(SEARCH("Revenue",'Fact_Financials- New'!D4:D7815)))} -> 20240131 | C1272: Americas | D1272: Product Revenue | E1272: Sales | F1272: 1 | G1272: 656646
B1273: 20240131 | C1273: Americas | D1273: Product Revenue | E1273: Sales | F1273: 2 | G1273: 671674
B1274: 20240131 | C1274: Americas | D1274: Product Revenue | E1274: Marketing | F1274: 1 | G1274: 101505
B1275: 20240131 | C1275: Americas | D1275: Product Revenue | E1275: Marketing | F1275: 2 | G1275: 111946
B1276: 20240131 | C1276: Americas | D1276: Product Revenue | E1276: Operations | F1276: 1 | G1276: 314202
B1277: 20240131 | C1277: Americas | D1277: Product Revenue | E1277: Operations | F1277: 2 | G1277: 335837
B1278: 20240131 | C1278: EMEA | D1278: Product Revenue | E1278: Sales | F1278: 1 | G1278: 444010
B1279: 20240131 | C1279: EMEA | D1279: Product Revenue | E1279: Sales | F1279: 2 | G1279: 477635
B1280: 20240131 | C1280: EMEA | D1280: Product Revenue | E1280: Marketing | F1280: 1 | G1280: 78716
B1281: 20240131 | C1281: EMEA | D1281: Product Revenue | E1281: Marketing | F1281: 2 | G1281: 79606
B1282: 20240131 | C1282: EMEA | D1282: Product Revenue | E1282: Operations | F1282: 1 | G1282: 234501
B1283: 20240131 | C1283: EMEA | D1283: Product Revenue | E1283: Operations | F1283: 2 | G1283: 238817
B1284: 20240131 | C1284: APAC | D1284: Product Revenue | E1284: Sales | F1284: 1 | G1284: 345631
... B2783: 20261231 | C2783: APAC | D2783: Services Revenue | E2783: Operations | F2783: 3 | G2783: 183098
B2786: Filter D — All Actuals (ScenarioKey=1) | H2786: ="Rows: "&ROWS(_xlfn.ANCHORARRAY(B2788)) -> Rows: 3348
B2787: DateKey | C2787: EntityKey | D2787: AccountKey | E2787: DeptKey | F2787: ScenarioKey | G2787: Amount
B2788: {=_xlfn._xlws.FILTER('Fact_Financials- New'!B4:G7815,'Fact_Financials- New'!F4:F7815=1)} -> 20240131 | C2788: Americas | D2788: Product Revenue | E2788: Sales | F2788: 1 | G2788: 656646
B2789: 20240131 | C2789: Americas | D2789: Product Revenue | E2789: Marketing | F2789: 1 | G2789: 101505
B2790: 20240131 | C2790: Americas | D2790: Product Revenue | E2790: Operations | F2790: 1 | G2790: 314202
B2791: 20240131 | C2791: EMEA | D2791: Product Revenue | E2791: Sales | F2791: 1 | G2791: 444010
...

Sheet Change Log
A1: Date | B1: Changed By | C1: Sheet(s) Affected | D1: Change Description | E1: Reason
A2: 46195 | B2: Claude | C2: Workbook Overview, Claude Log, Change Log | D2: Refreshed Workbook Overview from 17 stale sheets to 6 actual sheets (2 sections). Created Claude Log and Change Log sheets. | E2: User requested /workbook-overview refresh — many sheets listed in TOC no longer exist in workbook

Sheet Claude Log
A1: Turn # | B1: Date | C1: User Request | D1: Action Taken | E1: Details | F1: Outcome
A2: 1 | B2: 46195 | C2: Refresh the Workbook Overview using /workbook-overview skill | D2: Cleared stale 17-sheet TOC, rebuilt to match actual 6 sheets across 2 sections | E2: Cleared rows 7-43. Rebuilt with Navigation & Reference (2 sheets: Workbook Overview, Read Me) and Source Data & Engine (4 sheets: OG, New, Rolled Act, Dynamic Extracts). Used CELL("filename") formulas for dynamic sheet names, sequential counter formulas, yellow input cells for Section/Description/Type. Applied alternating banding, row grouping, summary block with SUM formula. Created Claude Log and Change Log sheets. | F2: Workbook Overview now shows 6 actual sheets in 2 collapsible sections. All formulas verified. Summary total = 6.
